Metadata-Version: 2.1
Name: fail2slack
Version: 0.4.0
Summary: Send fail2ban jail status updates to Slack.
Home-page: https://github.com/asdfdotdev/fail2slack
Author: Chris Carlevato
Author-email: hello@asdf.dev
License: GPL-2.0
Keywords: fail2ban,slack
Platform: UNKNOWN
Classifier: License :: OSI Approved :: GNU General Public License v2 (GPLv2)
Classifier: Programming Language :: Python :: 3.7
Classifier: Programming Language :: Python :: 3.8
Classifier: Programming Language :: Python :: 3.9
Classifier: Programming Language :: Python :: 3.10
Classifier: Topic :: Security
Classifier: Topic :: System
Classifier: Topic :: Utilities
License-File: LICENSE
